pyioc3/__init__.py
pyioc3/adapters.py
pyioc3/autowire.py
pyioc3/bound_member.py
pyioc3/bound_member_factory.py
pyioc3/builder.py
pyioc3/errors.py
pyioc3/interface.py
pyioc3/queued_cycle_test.py
pyioc3/scope_container.py
pyioc3/scope_enum.py
pyioc3/static_container.py
pyioc3/static_container_builder.py
pyioc3-1.6.3.dist-info/licenses/LICENSE
pyioc3-1.6.3.dist-info/METADATA
pyioc3-1.6.3.dist-info/WHEEL
pyioc3-1.6.3.dist-info/top_level.txt
pyioc3-1.6.3.dist-info/RECORD
